sourdough/__init__.py
sourdough/sd.py
sourdough/sourdough.py
sourdough/cli/__init__.py
sourdough/cli/commands.py
sourdough-1.0.2.dist-info/METADATA
sourdough-1.0.2.dist-info/WHEEL
sourdough-1.0.2.dist-info/entry_points.txt
sourdough-1.0.2.dist-info/top_level.txt
sourdough-1.0.2.dist-info/RECORD
