Metadata-Version: 2.1
Name: sourdough
Version: 1.0.2
Summary: sourdough is a tool to make an instance automatically register with Chef during boot
Home-page: https://github.com/unixorn/sourdough
Author: Joe Block
Author-email: jpb@unixorn.net
License: UNKNOWN
Download-URL: https://github.com/unixorn/sourdough/tarball/1.0.2
Keywords: aws,chef,cloud,configuration-management,ec2
Platform: UNKNOWN
Classifier: Development Status :: 3 - Alpha
Classifier: Operating System :: POSIX
Classifier: License :: OSI Approved :: Apache Software License
Classifier: Programming Language :: Python :: 2.6
Classifier: Topic :: System :: Systems Administration
Requires-Dist: boto (>=2.38.0)
Requires-Dist: haze (>=0.0.13)
Requires-Dist: logrus (>=0.0.2)
Requires-Dist: pytoml (>=0.1.11)
Requires-Dist: pyvim (>=2.0.24)
Requires-Dist: pyvmomi (>=6.7.1.2018.12)
Requires-Dist: six (>=1.12.0)
